<?xml version="1.0" encoding="UTF-8"?>
<objects serializationModel="Studio.02.03.00">
	<object class="AudioFile" id="{33e391f2-40b5-4754-919d-2005fb7a6c3d}">
		<property name="assetPath">
			<value>Hero good ending 1.wav</value>
		</property>
		<property name="isStreaming">
			<value>true</value>
		</property>
		<property name="frequencyInKHz">
			<value>48</value>
		</property>
		<property name="channelCount">
			<value>2</value>
		</property>
		<property name="length">
			<value>42.611145833333332</value>
		</property>
		<relationship name="masterAssetFolder">
			<destination>{0402de1f-0e62-4686-a543-a24fe43332e8}</destination>
		</relationship>
	</object>
</objects>
